Verilog/Basic examples/Exp5/Contador.v
module contador(clk,reset,data);

parameter nbits = 2;
input wire clk;
input wire reset;
output reg [nbits-1:0] data = 0;  

always @(posedge clk) 
begin
if (reset==0)	begin
  data <= data + 1;
end
else begin
data=0;
end
end
endmodule

Verilog/Basic examples/Exp5/ContadorTB.v
`timescale 1us/10ns
module ContadorTB;

reg clk;

wire out1; 
reg reset1;


wire [3:0] out2; 
reg reset2;


wire [7:0] out3; 
reg reset3;



contador b(clk,reset1,out1);
contador #(.nbits(4))bb(clk,reset2,out2);
contador #(.nbits(8))bbb(clk,reset3,out3);
integer errores =0;

initial begin
$dumpfile("wave_Contador.vcd");
$dumpvars(0,ContadorTB); 
end

initial begin
clk=0;

forever
begin




clk=~clk; 




#10;






end
end


initial begin
reset1=1;
reset2=1;
reset3=1;
forever
begin

if (out1!=1)
reset1=0;
else
reset1=1;

if (out2!=3)
reset2=0;
else
reset2=1;


if (out3!=7)
reset3=0;
else
reset3=1; 

#1

if (out1==0)begin
if (reset1==0)
errores=errores+1;
end

if (out2==0)begin
if (reset2==0)
errores=errores+1;
end

if (out3==0)begin
if (reset3==0)
errores=errores+1;
end

#19;
end


end



initial begin
#500;
if (errores==0)
$display ("No hay errores");
else
$display ("Se encontraron","%d",errores," errores");
 $finish;
end
endmodule

Verilog/Basic examples/Exp5/wave_Contador.vcd
$date
	Tue Mar 16 14:27:37 2021
$end
$version
	ModelSim Version 10.5b
$end
$timescale
	10ns
$end

$scope module ContadorTB $end
$var reg 1 ! clk $end
$var wire 1 " out1 $end
$var reg 1 # reset1 $end
$var wire 1 $ out2 [3] $end
$var wire 1 % out2 [2] $end
$var wire 1 & out2 [1] $end
$var wire 1 ' out2 [0] $end
$var reg 1 ( reset2 $end
$var wire 1 ) out3 [7] $end
$var wire 1 * out3 [6] $end
$var wire 1 + out3 [5] $end
$var wire 1 , out3 [4] $end
$var wire 1 - out3 [3] $end
$var wire 1 . out3 [2] $end
$var wire 1 / out3 [1] $end
$var wire 1 0 out3 [0] $end
$var reg 1 1 reset3 $end
$var integer 32 2 errores $end

$scope module b $end
$var parameter 32 3 nbits $end
$var wire 1 4 clk $end
$var wire 1 5 reset $end
$var reg 2 6 data [1:0] $end
$upscope $end

$scope module bb $end
$var parameter 32 7 nbits $end
$var wire 1 8 clk $end
$var wire 1 9 reset $end
$var reg 4 : data [3:0] $end
$upscope $end

$scope module bbb $end
$var parameter 32 ; nbits $end
$var wire 1 < clk $end
$var wire 1 = reset $end
$var reg 8 > data [7:0] $end
$upscope $end
$upscope $end
$enddefinitions $end
#0
$dumpvars
1!
1#
1(
11
b0 6
b0 :
b0 >
b10 3
b100 7
b1000 ;
b0 2
0"
0'
0&
0%
0$
00
0/
0.
0-
0,
0+
0*
0)
1=
1<
19
18
15
14
$end
#1000
0!
04
08
0<
#2000
0#
0(
01
1!
05
09
0=
14
18
1<
b1 >
b1 :
b1 6
1"
1'
10
#3000
0!
04
08
0<
#4000
1#
1!
15
14
18
1<
b0 6
0"
b10 >
b10 :
0'
1&
00
1/
#5000
0!
04
08
0<
#6000
0#
1!
05
14
18
1<
b11 >
b11 :
b1 6
1"
1'
10
#7000
0!
04
08
0<
#8000
1#
1(
1!
15
19
14
18
1<
b0 :
b0 6
0"
0'
0&
b100 >
00
0/
1.
#9000
0!
04
08
0<
#10000
0#
0(
1!
05
09
14
18
1<
b101 >
b1 :
b1 6
1"
1'
10
#11000
0!
04
08
0<
#12000
1#
1!
15
14
18
1<
b0 6
0"
b110 >
b10 :
0'
1&
00
1/
#13000
0!
04
08
0<
#14000
0#
1!
05
14
18
1<
b111 >
b11 :
b1 6
1"
1'
10
#15000
0!
04
08
0<
#16000
1#
1(
11
1!
15
19
1=
14
18
1<
b0 >
b0 :
b0 6
0"
0'
0&
00
0/
0.
#17000
0!
04
08
0<
#18000
0#
0(
01
1!
05
09
0=
14
18
1<
b1 >
b1 :
b1 6
1"
1'
10
#19000
0!
04
08
0<
#20000
1#
1!
15
14
18
1<
b0 6
0"
b10 >
b10 :
0'
1&
00
1/
#21000
0!
04
08
0<
#22000
0#
1!
05
14
18
1<
b11 >
b11 :
b1 6
1"
1'
10
#23000
0!
04
08
0<
#24000
1#
1(
1!
15
19
14
18
1<
b0 :
b0 6
0"
0'
0&
b100 >
00
0/
1.
#25000
0!
04
08
0<
#26000
0#
0(
1!
05
09
14
18
1<
b101 >
b1 :
b1 6
1"
1'
10
#27000
0!
04
08
0<
#28000
1#
1!
15
14
18
1<
b0 6
0"
b110 >
b10 :
0'
1&
00
1/
#29000
0!
04
08
0<
#30000
0#
1!
05
14
18
1<
b111 >
b11 :
b1 6
1"
1'
10
#31000
0!
04
08
0<
#32000
1#
1(
11
1!
15
19
1=
14
18
1<
b0 >
b0 :
b0 6
0"
0'
0&
00
0/
0.
#33000
0!
04
08
0<
#34000
0#
0(
01
1!
05
09
0=
14
18
1<
b1 >
b1 :
b1 6
1"
1'
10
#35000
0!
04
08
0<
#36000
1#
1!
15
14
18
1<
b0 6
0"
b10 >
b10 :
0'
1&
00
1/
#37000
0!
04
08
0<
#38000
0#
1!
05
14
18
1<
b11 >
b11 :
b1 6
1"
1'
10
#39000
0!
04
08
0<
#40000
1#
1(
1!
15
19
14
18
1<
b0 :
b0 6
0"
0'
0&
b100 >
00
0/
1.
#41000
0!
04
08
0<
#42000
0#
0(
1!
05
09
14
18
1<
b101 >
b1 :
b1 6
1"
1'
10
#43000
0!
04
08
0<
#44000
1#
1!
15
14
18
1<
b0 6
0"
b110 >
b10 :
0'
1&
00
1/
#45000
0!
04
08
0<
#46000
0#
1!
05
14
18
1<
b111 >
b11 :
b1 6
1"
1'
10
#47000
0!
04
08
0<
#48000
1#
1(
11
1!
15
19
1=
14
18
1<
b0 >
b0 :
b0 6
0"
0'
0&
00
0/
0.
