Verilog/Basic examples/Exp3/Mux.v
module mux_4x1(a,b,c,d,sel,out);
parameter WIDTH = 16;
output reg [WIDTH-1:0]out;
input [WIDTH-1:0]a,b,c,d;
input [1:0] sel;
always@(sel or a or b or c or d)
begin
	case(sel)
		2'b00: out = a;
		2'b01: out = b;
		2'b10: out = c;
		2'b11: out = d;
	endcase
end
endmodule

Verilog/Basic examples/Exp3/MuxTB.v
//`timescale 10ns/ 10ps;
`timescale 1us/10ns
module MuxTB;
//Prueba 16 bits
reg  [15:0]A,B,C,D;
reg [1:0] S; 
wire [15:0]O;
//Prueba 8 bits
reg  [7:0] A2,B2,C2,D2;
reg [1:0] S2; 
wire [7:0]O2;

//Prueba 4 bits
reg  [3:0] A4,B4,C4,D4;
reg [1:0] S4; 
wire [3:0]O4;

mux_4x1 uut(A,B,C,D,S,O);
mux_4x1#(.WIDTH(8))uuq(A2,B2,C2,D2,S2,O2);
mux_4x1#(.WIDTH(4))uup(A4,B4,C4,D4,S4,O4);


initial begin
$dumpfile("wave_mux4x1.vcd");
$dumpvars(0,MuxTB); 
end
integer i;
initial begin

A=16'b0000000110000000;
B=16'b0000000000000001;
C=16'b1000000000000000;
D=16'b0000010000000000;
S=2'b00;

A2=8'b00000001;
B2=8'b10000000;
C2=8'b01100000;
D2=8'b00001100;
S2=8'b00000000;

A4=4'b0100;
B4=4'b0010;
C4=4'b0001;
D4=4'b0110;
S4=2'b00;

for(i=0; i<51; i=i+1)begin

	A=A+1;
	B=B+1;
	C=C+1;
	D=D+1;
	S=S+1;

	A2=A2+1;
	B2=B2+1;
	C2=C2+1;
	D2=D2+1;
	S2=S2+1;

	A4=A4+1;
	B4=B4+1;
	C4=C4+1;
	D4=D4+1;
	S4=S4+1;
	#2;
end
end
endmodule

Verilog/Basic examples/Exp3/wave_mux4x1.vcd
$date
	Thu Mar 11 12:51:46 2021
$end
$version
	ModelSim Version 10.5b
$end
$timescale
	10ns
$end

$scope module MuxTB $end
$var reg 16 ! A [15:0] $end
$var reg 16 " B [15:0] $end
$var reg 16 # C [15:0] $end
$var reg 16 $ D [15:0] $end
$var reg 2 % S [1:0] $end
$var wire 1 & O [15] $end
$var wire 1 ' O [14] $end
$var wire 1 ( O [13] $end
$var wire 1 ) O [12] $end
$var wire 1 * O [11] $end
$var wire 1 + O [10] $end
$var wire 1 , O [9] $end
$var wire 1 - O [8] $end
$var wire 1 . O [7] $end
$var wire 1 / O [6] $end
$var wire 1 0 O [5] $end
$var wire 1 1 O [4] $end
$var wire 1 2 O [3] $end
$var wire 1 3 O [2] $end
$var wire 1 4 O [1] $end
$var wire 1 5 O [0] $end
$var reg 8 6 A2 [7:0] $end
$var reg 8 7 B2 [7:0] $end
$var reg 8 8 C2 [7:0] $end
$var reg 8 9 D2 [7:0] $end
$var reg 2 : S2 [1:0] $end
$var wire 1 ; O2 [7] $end
$var wire 1 < O2 [6] $end
$var wire 1 = O2 [5] $end
$var wire 1 > O2 [4] $end
$var wire 1 ? O2 [3] $end
$var wire 1 @ O2 [2] $end
$var wire 1 A O2 [1] $end
$var wire 1 B O2 [0] $end
$var reg 4 C A4 [3:0] $end
$var reg 4 D B4 [3:0] $end
$var reg 4 E C4 [3:0] $end
$var reg 4 F D4 [3:0] $end
$var reg 2 G S4 [1:0] $end
$var wire 1 H O4 [3] $end
$var wire 1 I O4 [2] $end
$var wire 1 J O4 [1] $end
$var wire 1 K O4 [0] $end
$var integer 32 L i $end

$scope module uut $end
$var parameter 32 M WIDTH $end
$var reg 16 N out [15:0] $end
$var wire 1 O a [15] $end
$var wire 1 P a [14] $end
$var wire 1 Q a [13] $end
$var wire 1 R a [12] $end
$var wire 1 S a [11] $end
$var wire 1 T a [10] $end
$var wire 1 U a [9] $end
$var wire 1 V a [8] $end
$var wire 1 W a [7] $end
$var wire 1 X a [6] $end
$var wire 1 Y a [5] $end
$var wire 1 Z a [4] $end
$var wire 1 [ a [3] $end
$var wire 1 \ a [2] $end
$var wire 1 ] a [1] $end
$var wire 1 ^ a [0] $end
$var wire 1 _ b [15] $end
$var wire 1 ` b [14] $end
$var wire 1 a b [13] $end
$var wire 1 b b [12] $end
$var wire 1 c b [11] $end
$var wire 1 d b [10] $end
$var wire 1 e b [9] $end
$var wire 1 f b [8] $end
$var wire 1 g b [7] $end
$var wire 1 h b [6] $end
$var wire 1 i b [5] $end
$var wire 1 j b [4] $end
$var wire 1 k b [3] $end
$var wire 1 l b [2] $end
$var wire 1 m b [1] $end
$var wire 1 n b [0] $end
$var wire 1 o c [15] $end
$var wire 1 p c [14] $end
$var wire 1 q c [13] $end
$var wire 1 r c [12] $end
$var wire 1 s c [11] $end
$var wire 1 t c [10] $end
$var wire 1 u c [9] $end
$var wire 1 v c [8] $end
$var wire 1 w c [7] $end
$var wire 1 x c [6] $end
$var wire 1 y c [5] $end
$var wire 1 z c [4] $end
$var wire 1 { c [3] $end
$var wire 1 | c [2] $end
$var wire 1 } c [1] $end
$var wire 1 ~ c [0] $end
$var wire 1 !! d [15] $end
$var wire 1 "! d [14] $end
$var wire 1 #! d [13] $end
$var wire 1 $! d [12] $end
$var wire 1 %! d [11] $end
$var wire 1 &! d [10] $end
$var wire 1 '! d [9] $end
$var wire 1 (! d [8] $end
$var wire 1 )! d [7] $end
$var wire 1 *! d [6] $end
$var wire 1 +! d [5] $end
$var wire 1 ,! d [4] $end
$var wire 1 -! d [3] $end
$var wire 1 .! d [2] $end
$var wire 1 /! d [1] $end
$var wire 1 0! d [0] $end
$var wire 1 1! sel [1] $end
$var wire 1 2! sel [0] $end
$upscope $end

$scope module uuq $end
$var parameter 32 3! WIDTH $end
$var reg 8 4! out [7:0] $end
$var wire 1 5! a [7] $end
$var wire 1 6! a [6] $end
$var wire 1 7! a [5] $end
$var wire 1 8! a [4] $end
$var wire 1 9! a [3] $end
$var wire 1 :! a [2] $end
$var wire 1 ;! a [1] $end
$var wire 1 <! a [0] $end
$var wire 1 =! b [7] $end
$var wire 1 >! b [6] $end
$var wire 1 ?! b [5] $end
$var wire 1 @! b [4] $end
$var wire 1 A! b [3] $end
$var wire 1 B! b [2] $end
$var wire 1 C! b [1] $end
$var wire 1 D! b [0] $end
$var wire 1 E! c [7] $end
$var wire 1 F! c [6] $end
$var wire 1 G! c [5] $end
$var wire 1 H! c [4] $end
$var wire 1 I! c [3] $end
$var wire 1 J! c [2] $end
$var wire 1 K! c [1] $end
$var wire 1 L! c [0] $end
$var wire 1 M! d [7] $end
$var wire 1 N! d [6] $end
$var wire 1 O! d [5] $end
$var wire 1 P! d [4] $end
$var wire 1 Q! d [3] $end
$var wire 1 R! d [2] $end
$var wire 1 S! d [1] $end
$var wire 1 T! d [0] $end
$var wire 1 U! sel [1] $end
$var wire 1 V! sel [0] $end
$upscope $end

$scope module uup $end
$var parameter 32 W! WIDTH $end
$var reg 4 X! out [3:0] $end
$var wire 1 Y! a [3] $end
$var wire 1 Z! a [2] $end
$var wire 1 [! a [1] $end
$var wire 1 \! a [0] $end
$var wire 1 ]! b [3] $end
$var wire 1 ^! b [2] $end
$var wire 1 _! b [1] $end
$var wire 1 `! b [0] $end
$var wire 1 a! c [3] $end
$var wire 1 b! c [2] $end
$var wire 1 c! c [1] $end
$var wire 1 d! c [0] $end
$var wire 1 e! d [3] $end
$var wire 1 f! d [2] $end
$var wire 1 g! d [1] $end
$var wire 1 h! d [0] $end
$var wire 1 i! sel [1] $end
$var wire 1 j! sel [0] $end
$upscope $end
$upscope $end
$enddefinitions $end
#0
$dumpvars
b110000001 !
b10 "
b1000000000000001 #
b10000000001 $
b1 %
b10 6
b10000001 7
b1100001 8
b1101 9
b1 :
b101 C
b11 D
b10 E
b111 F
b1 G
b10 N
b10000001 4!
b11 X!
b10000 M
b1000 3!
b100 W!
b0 L
05
14
03
02
01
00
0/
0.
0-
0,
0+
0*
0)
0(
0'
0&
1B
0A
0@
0?
0>
0=
0<
1;
1K
1J
0I
0H
1j!
0i!
1h!
1g!
1f!
0e!
0d!
1c!
0b!
0a!
1`!
1_!
0^!
0]!
1\!
0[!
1Z!
0Y!
1V!
0U!
1T!
0S!
1R!
1Q!
0P!
0O!
0N!
0M!
1L!
0K!
0J!
0I!
0H!
1G!
1F!
0E!
1D!
0C!
0B!
0A!
0@!
0?!
0>!
1=!
0<!
1;!
0:!
09!
08!
07!
06!
05!
12!
01!
10!
0/!
0.!
0-!
0,!
0+!
0*!
0)!
0(!
0'!
1&!
0%!
0$!
0#!
0"!
0!!
1~
0}
0|
0{
0z
0y
0x
0w
0v
0u
0t
0s
0r
0q
0p
1o
0n
1m
0l
0k
0j
0i
0h
0g
0f
0e
0d
0c
0b
0a
0`
0_
1^
0]
0\
0[
0Z
0Y
0X
1W
1V
0U
0T
0S
0R
0Q
0P
0O
$end
#200
b1 L
b110000010 !
b11 "
b1000000000000010 #
b10000000010 $
b10 %
b11 6
b10000010 7
b1100010 8
b1110 9
b10 :
b110 C
b100 D
b11 E
b1000 F
b10 G
0j!
1i!
0h!
0g!
0f!
1e!
1d!
0`!
0_!
1^!
0\!
1[!
0V!
1U!
0T!
1S!
0L!
1K!
0D!
1C!
1<!
02!
11!
00!
1/!
0~
1}
1n
0^
1]
b1000000000000010 N
b1100010 4!
0B
1A
1=
1<
0;
1&
#400
b10 L
b110000011 !
b100 "
b1000000000000011 #
b10000000011 $
b11 %
b100 6
b10000011 7
b1100011 8
b1111 9
b11 :
b111 C
b101 D
b100 E
b1001 F
b11 G
1j!
1h!
0d!
0c!
1b!
1`!
1\!
1V!
1T!
1L!
1D!
0<!
0;!
1:!
12!
10!
1~
0n
0m
1l
1^
b10000000011 N
b1111 4!
b1001 X!
0J
1H
1B
1@
1?
0=
0<
15
1+
0&
#600
b11 L
b110000100 !
b101 "
b1000000000000100 #
b10000000100 $
b0 %
b101 6
b10000100 7
b1100100 8
b10000 9
b0 :
b1000 C
b110 D
b101 E
b1010 F
b0 G
0j!
0i!
0h!
1g!
1d!
0`!
1_!
0\!
0[!
0Z!
1Y!
0V!
0U!
0T!
0S!
0R!
0Q!
1P!
0L!
0K!
1J!
0D!
0C!
1B!
1<!
02!
01!
00!
0/!
1.!
0~
0}
1|
1n
0^
0]
1\
b110000100 N
b101 4!
b1000 X!
0K
0A
0?
05
04
13
1.
1-
0+
#800
b100 L
b110000101 !
b110 "
b1000000000000101 #
b10000000101 $
b1 %
b110 6
b10000101 7
b1100101 8
b10001 9
b1 :
b1001 C
b111 D
b110 E
b1011 F
b1 G
1j!
1h!
0d!
1c!
1`!
1\!
1V!
1T!
1L!
1D!
0<!
1;!
12!
10!
1~
0n
1m
1^
b110 N
b10000101 4!
b111 X!
1K
1J
1I
0H
1;
14
0.
0-
#1000
b101 L
b110000110 !
b111 "
b1000000000000110 #
b10000000110 $
b10 %
b111 6
b10000110 7
b1100110 8
b10010 9
b10 :
b1010 C
b1000 D
b111 E
b1100 F
b10 G
0j!
1i!
0h!
0g!
1f!
1d!
0`!
0_!
0^!
1]!
0\!
1[!
0V!
1U!
0T!
1S!
0L!
1K!
0D!
1C!
1<!
02!
11!
00!
1/!
0~
1}
1n
0^
1]
b1000000000000110 N
b1100110 4!
0B
1A
1=
1<
0;
1&
#1200
b110 L
b110000111 !
b1000 "
b1000000000000111 #
b10000000111 $
b11 %
b1000 6
b10000111 7
b1100111 8
b10011 9
b11 :
b1011 C
b1001 D
b1000 E
b1101 F
b11 G
1j!
1h!
0d!
0c!
0b!
1a!
1`!
1\!
1V!
1T!
1L!
1D!
0<!
0;!
0:!
19!
12!
10!
1~
0n
0m
0l
1k
1^
b10000000111 N
b10011 4!
b1101 X!
0J
1H
1B
0@
1>
0=
0<
15
1+
0&
#1400
b111 L
b110001000 !
b1001 "
b1000000000001000 #
b10000001000 $
b0 %
b1001 6
b10001000 7
b1101000 8
b10100 9
b0 :
b1100 C
b1010 D
b1001 E
b1110 F
b0 G
0j!
0i!
0h!
1g!
1d!
0`!
1_!
0\!
0[!
1Z!
0V!
0U!
0T!
0S!
1R!
0L!
0K!
0J!
1I!
0D!
0C!
0B!
1A!
1<!
02!
01!
00!
0/!
0.!
1-!
0~
0}
0|
1{
1n
0^
0]
0\
1[
b110001000 N
b1001 4!
b1100 X!
0K
0A
1?
0>
05
04
03
12
1.
1-
0+
#1600
b1000 L
b110001001 !
b1010 "
b1000000000001001 #
b10000001001 $
b1 %
b1010 6
b10001001 7
b1101001 8
b10101 9
b1 :
b1101 C
b1011 D
b1010 E
b1111 F
b1 G
1j!
1h!
0d!
1c!
1`!
1\!
1V!
1T!
1L!
1D!
0<!
1;!
12!
10!
1~
0n
1m
1^
b1010 N
b10001001 4!
b1011 X!
1K
1J
0I
1;
14
0.
0-
#1800
b1001 L
b110001010 !
b1011 "
b1000000000001010 #
b10000001010 $
b10 %
b1011 6
b10001010 7
b1101010 8
b10110 9
b10 :
b1110 C
b1100 D
b1011 E
b0 F
b10 G
0j!
1i!
0h!
0g!
0f!
0e!
1d!
0`!
0_!
1^!
0\!
1[!
0V!
1U!
0T!
1S!
0L!
1K!
0D!
1C!
1<!
02!
11!
00!
1/!
0~
1}
1n
0^
1]
b1000000000001010 N
b1101010 4!
0B
1A
1=
1<
0;
1&
#2000
b1010 L
b110001011 !
b1100 "
b1000000000001011 #
b10000001011 $
b11 %
b1100 6
b10001011 7
b1101011 8
b10111 9
b11 :
b1111 C
b1101 D
b1100 E
b1 F
b11 G
1j!
1h!
0d!
0c!
1b!
1`!
1\!
1V!
1T!
1L!
1D!
0<!
0;!
1:!
12!
10!
1~
0n
0m
1l
1^
b10000001011 N
b10111 4!
b1 X!
0J
0H
1B
1@
0?
1>
0=
0<
15
1+
0&
#2200
b1011 L
b110001100 !
b1101 "
b1000000000001100 #
b10000001100 $
b0 %
b1101 6
b10001100 7
b1101100 8
b11000 9
b0 :
b0 C
b1110 D
b1101 E
b10 F
b0 G
0j!
0i!
0h!
1g!
1d!
0`!
1_!
0\!
0[!
0Z!
0Y!
0V!
0U!
0T!
0S!
0R!
1Q!
0L!
0K!
1J!
0D!
0C!
1B!
1<!
02!
01!
00!
0/!
1.!
0~
0}
1|
1n
0^
0]
1\
b110001100 N
b1101 4!
b0 X!
0K
0A
1?
0>
05
04
13
1.
1-
0+
#2400
b1100 L
b110001101 !
b1110 "
b1000000000001101 #
b10000001101 $
b1 %
b1110 6
b10001101 7
b1101101 8
b11001 9
b1 :
b1 C
b1111 D
b1110 E
b11 F
b1 G
1j!
1h!
0d!
1c!
1`!
1\!
1V!
1T!
1L!
1D!
0<!
1;!
12!
10!
1~
0n
1m
1^
b1110 N
b10001101 4!
b1111 X!
1K
1J
1I
1H
1;
14
0.
0-
#2600
b1101 L
b110001110 !
b1111 "
b1000000000001110 #
b10000001110 $
b10 %
b1111 6
b10001110 7
b1101110 8
b11010 9
b10 :
b10 C
b0 D
b1111 E
b100 F
b10 G
0j!
1i!
0h!
0g!
1f!
1d!
0`!
0_!
0^!
0]!
0\!
1[!
0V!
1U!
0T!
1S!
0L!
1K!
0D!
1C!
1<!
02!
11!
00!
1/!
0~
1}
1n
0^
1]
b1000000000001110 N
b1101110 4!
0B
1A
1=
1<
0;
1&
#2800
b1110 L
b110001111 !
b10000 "
b1000000000001111 #
b10000001111 $
b11 %
b10000 6
b10001111 7
b1101111 8
b11011 9
b11 :
b11 C
b1 D
b0 E
b101 F
b11 G
1j!
1h!
0d!
0c!
0b!
0a!
1`!
1\!
1V!
1T!
1L!
1D!
0<!
0;!
0:!
09!
18!
12!
10!
1~
0n
0m
0l
0k
1j
1^
b10000001111 N
b11011 4!
b101 X!
0J
0H
1B
0@
1>
0=
0<
15
1+
0&
#3000
b1111 L
b110010000 !
b10001 "
b1000000000010000 #
b10000010000 $
b0 %
b10001 6
b10010000 7
b1110000 8
b11100 9
b0 :
b100 C
b10 D
b1 E
b110 F
b0 G
0j!
0i!
0h!
1g!
1d!
0`!
1_!
0\!
0[!
1Z!
0V!
0U!
0T!
0S!
1R!
0L!
0K!
0J!
0I!
1H!
0D!
0C!
0B!
0A!
1@!
1<!
02!
01!
00!
0/!
0.!
0-!
1,!
0~
0}
0|
0{
1z
1n
0^
0]
0\
0[
1Z
b110010000 N
b10001 4!
b100 X!
0K
0A
0?
05
04
03
02
11
1.
1-
0+
#3200
b10000 L
b110010001 !
b10010 "
b1000000000010001 #
b10000010001 $
b1 %
b10010 6
b10010001 7
b1110001 8
b11101 9
b1 :
b101 C
b11 D
b10 E
b111 F
b1 G
1j!
1h!
0d!
1c!
1`!
1\!
1V!
1T!
1L!
1D!
0<!
1;!
12!
10!
1~
0n
1m
1^
b10010 N
b10010001 4!
b11 X!
1K
1J
0I
1;
14
0.
0-
#3400
b10001 L
b110010010 !
b10011 "
b1000000000010010 #
b10000010010 $
b10 %
b10011 6
b10010010 7
b1110010 8
b11110 9
b10 :
b110 C
b100 D
b11 E
b1000 F
b10 G
0j!
1i!
0h!
0g!
0f!
1e!
1d!
0`!
0_!
1^!
0\!
1[!
0V!
1U!
0T!
1S!
0L!
1K!
0D!
1C!
1<!
02!
11!
00!
1/!
0~
1}
1n
0^
1]
b1000000000010010 N
b1110010 4!
0B
1A
1=
1<
0;
1&
#3600
b10010 L
b110010011 !
b10100 "
b1000000000010011 #
b10000010011 $
b11 %
b10100 6
b10010011 7
b1110011 8
b11111 9
b11 :
b111 C
b101 D
b100 E
b1001 F
b11 G
1j!
1h!
0d!
0c!
1b!
1`!
1\!
1V!
1T!
1L!
1D!
0<!
0;!
1:!
12!
10!
1~
0n
0m
1l
1^
b10000010011 N
b11111 4!
b1001 X!
0J
1H
1B
1@
1?
0=
0<
15
1+
0&
#3800
b10011 L
b110010100 !
b10101 "
b1000000000010100 #
b10000010100 $
b0 %
b10101 6
b10010100 7
b1110100 8
b100000 9
b0 :
b1000 C
b110 D
b101 E
b1010 F
b0 G
0j!
0i!
0h!
1g!
1d!
0`!
1_!
0\!
0[!
0Z!
1Y!
0V!
0U!
0T!
0S!
0R!
0Q!
0P!
1O!
0L!
0K!
1J!
0D!
0C!
1B!
1<!
02!
01!
00!
0/!
1.!
0~
0}
1|
1n
0^
0]
1\
b110010100 N
b10101 4!
b1000 X!
0K
0A
0?
05
04
13
1.
1-
0+
#4000
b10100 L
b110010101 !
b10110 "
b1000000000010101 #
b10000010101 $
b1 %
b10110 6
b10010101 7
b1110101 8
b100001 9
b1 :
b1001 C
b111 D
b110 E
b1011 F
b1 G
1j!
1h!
0d!
1c!
1`!
1\!
1V!
1T!
1L!
1D!
0<!
1;!
12!
10!
1~
0n
1m
1^
b10110 N
b10010101 4!
b111 X!
1K
1J
1I
0H
1;
14
0.
0-
#4200
b10101 L
b110010110 !
b10111 "
b1000000000010110 #
b10000010110 $
b10 %
b10111 6
b10010110 7
b1110110 8
b100010 9
b10 :
b1010 C
b1000 D
b111 E
b1100 F
b10 G
0j!
1i!
0h!
0g!
1f!
1d!
0`!
0_!
0^!
1]!
0\!
1[!
0V!
1U!
0T!
1S!
0L!
1K!
0D!
1C!
1<!
02!
11!
00!
1/!
0~
1}
1n
0^
1]
b1000000000010110 N
b1110110 4!
0B
1A
1=
1<
0;
1&
#4400
b10110 L
b110010111 !
b11000 "
b1000000000010111 #
b10000010111 $
b11 %
b11000 6
b10010111 7
b1110111 8
b100011 9
b11 :
b1011 C
b1001 D
b1000 E
b1101 F
b11 G
1j!
1h!
0d!
0c!
0b!
1a!
1`!
1\!
1V!
1T!
1L!
1D!
0<!
0;!
0:!
19!
12!
10!
1~
0n
0m
0l
1k
1^
b10000010111 N
b100011 4!
b1101 X!
0J
1H
1B
0@
0>
0<
15
1+
0&
#4600
b10111 L
b110011000 !
b11001 "
b1000000000011000 #
b10000011000 $
b0 %
b11001 6
b10011000 7
b1111000 8
b100100 9
b0 :
b1100 C
b1010 D
b1001 E
b1110 F
b0 G
0j!
0i!
0h!
1g!
1d!
0`!
1_!
0\!
0[!
1Z!
0V!
0U!
0T!
0S!
1R!
0L!
0K!
0J!
1I!
0D!
0C!
0B!
1A!
1<!
02!
01!
00!
0/!
0.!
1-!
0~
0}
0|
1{
1n
0^
0]
0\
1[
b110011000 N
b11001 4!
b1100 X!
0K
0A
1?
1>
0=
05
04
03
12
1.
1-
0+
#4800
b11000 L
b110011001 !
b11010 "
b1000000000011001 #
b10000011001 $
b1 %
b11010 6
b10011001 7
b1111001 8
b100101 9
b1 :
b1101 C
b1011 D
b1010 E
b1111 F
b1 G
1j!
1h!
0d!
1c!
1`!
1\!
1V!
1T!
1L!
1D!
0<!
1;!
12!
10!
1~
0n
1m
1^
b11010 N
b10011001 4!
b1011 X!
1K
1J
0I
1;
14
0.
0-
#5000
b11001 L
b110011010 !
b11011 "
b1000000000011010 #
b10000011010 $
b10 %
b11011 6
b10011010 7
b1111010 8
b100110 9
b10 :
b1110 C
b1100 D
b1011 E
b0 F
b10 G
0j!
1i!
0h!
0g!
0f!
0e!
1d!
0`!
0_!
1^!
0\!
1[!
0V!
1U!
0T!
1S!
0L!
1K!
0D!
1C!
1<!
02!
11!
00!
1/!
0~
1}
1n
0^
1]
b1000000000011010 N
b1111010 4!
0B
1A
1=
1<
0;
1&
#5200
b11010 L
b110011011 !
b11100 "
b1000000000011011 #
b10000011011 $
b11 %
b11100 6
b10011011 7
b1111011 8
b100111 9
b11 :
b1111 C
b1101 D
b1100 E
b1 F
b11 G
1j!
1h!
0d!
0c!
1b!
1`!
1\!
1V!
1T!
1L!
1D!
0<!
0;!
1:!
12!
10!
1~
0n
0m
1l
1^
b10000011011 N
b100111 4!
b1 X!
0J
0H
1B
1@
0?
0>
0<
15
1+
0&
#5400
b11011 L
b110011100 !
b11101 "
b1000000000011100 #
b10000011100 $
b0 %
b11101 6
b10011100 7
b1111100 8
b101000 9
b0 :
b0 C
b1110 D
b1101 E
b10 F
b0 G
0j!
0i!
0h!
1g!
1d!
0`!
1_!
0\!
0[!
0Z!
0Y!
0V!
0U!
0T!
0S!
0R!
1Q!
0L!
0K!
1J!
0D!
0C!
1B!
1<!
02!
01!
00!
0/!
1.!
0~
0}
1|
1n
0^
0]
1\
b110011100 N
b11101 4!
b0 X!
0K
0A
1?
1>
0=
05
04
13
1.
1-
0+
#5600
b11100 L
b110011101 !
b11110 "
b1000000000011101 #
b10000011101 $
b1 %
b11110 6
b10011101 7
b1111101 8
b101001 9
b1 :
b1 C
b1111 D
b1110 E
b11 F
b1 G
1j!
1h!
0d!
1c!
1`!
1\!
1V!
1T!
1L!
1D!
0<!
1;!
12!
10!
1~
0n
1m
1^
b11110 N
b10011101 4!
b1111 X!
1K
1J
1I
1H
1;
14
0.
0-
#5800
b11101 L
b110011110 !
b11111 "
b1000000000011110 #
b10000011110 $
b10 %
b11111 6
b10011110 7
b1111110 8
b101010 9
b10 :
b10 C
b0 D
b1111 E
b100 F
b10 G
0j!
1i!
0h!
0g!
1f!
1d!
0`!
0_!
0^!
0]!
0\!
1[!
0V!
1U!
0T!
1S!
0L!
1K!
0D!
1C!
1<!
02!
11!
00!
1/!
0~
1}
1n
0^
1]
b1000000000011110 N
b1111110 4!
0B
1A
1=
1<
0;
1&
#6000
b11110 L
b110011111 !
b100000 "
b1000000000011111 #
b10000011111 $
b11 %
b100000 6
b10011111 7
b1111111 8
b101011 9
b11 :
b11 C
b1 D
b0 E
b101 F
b11 G
1j!
1h!
0d!
0c!
0b!
0a!
1`!
1\!
1V!
1T!
1L!
1D!
0<!
0;!
0:!
09!
08!
17!
12!
10!
1~
0n
0m
0l
0k
0j
1i
1^
b10000011111 N
b101011 4!
b101 X!
0J
0H
1B
0@
0>
0<
15
1+
0&
#6200
b11111 L
b110100000 !
b100001 "
b1000000000100000 #
b10000100000 $
b0 %
b100001 6
b10100000 7
b10000000 8
b101100 9
b0 :
b100 C
b10 D
b1 E
b110 F
b0 G
0j!
0i!
0h!
1g!
1d!
0`!
1_!
0\!
0[!
1Z!
0V!
0U!
0T!
0S!
1R!
0L!
0K!
0J!
0I!
0H!
0G!
0F!
1E!
0D!
0C!
0B!
0A!
0@!
1?!
1<!
02!
01!
00!
0/!
0.!
0-!
0,!
1+!
0~
0}
0|
0{
0z
1y
1n
0^
0]
0\
0[
0Z
1Y
b110100000 N
b100001 4!
b100 X!
0K
0A
0?
05
04
03
02
01
10
1.
1-
0+
#6400
b100000 L
b110100001 !
b100010 "
b1000000000100001 #
b10000100001 $
b1 %
b100010 6
b10100001 7
b10000001 8
b101101 9
b1 :
b101 C
b11 D
b10 E
b111 F
b1 G
1j!
1h!
0d!
1c!
1`!
1\!
1V!
1T!
1L!
1D!
0<!
1;!
12!
10!
1~
0n
1m
1^
b100010 N
b10100001 4!
b11 X!
1K
1J
0I
1;
14
0.
0-
#6600
b100001 L
b110100010 !
b100011 "
b1000000000100010 #
b10000100010 $
b10 %
b100011 6
b10100010 7
b10000010 8
b101110 9
b10 :
b110 C
b100 D
b11 E
b1000 F
b10 G
0j!
1i!
0h!
0g!
0f!
1e!
1d!
0`!
0_!
1^!
0\!
1[!
0V!
1U!
0T!
1S!
0L!
1K!
0D!
1C!
1<!
02!
11!
00!
1/!
0~
1}
1n
0^
1]
b1000000000100010 N
b10000010 4!
0B
1A
0=
1&
#6800
b100010 L
b110100011 !
b100100 "
b1000000000100011 #
b10000100011 $
b11 %
b100100 6
b10100011 7
b10000011 8
b101111 9
b11 :
b111 C
b101 D
b100 E
b1001 F
b11 G
1j!
1h!
0d!
0c!
1b!
1`!
1\!
1V!
1T!
1L!
1D!
0<!
0;!
1:!
12!
10!
1~
0n
0m
1l
1^
b10000100011 N
b101111 4!
b1001 X!
0J
1H
1B
1@
1?
1=
0;
15
1+
0&
#7000
b100011 L
b110100100 !
b100101 "
b1000000000100100 #
b10000100100 $
b0 %
b100101 6
b10100100 7
b10000100 8
b110000 9
b0 :
b1000 C
b110 D
b101 E
b1010 F
b0 G
0j!
0i!
0h!
1g!
1d!
0`!
1_!
0\!
0[!
0Z!
1Y!
0V!
0U!
0T!
0S!
0R!
0Q!
1P!
0L!
0K!
1J!
0D!
0C!
1B!
1<!
02!
01!
00!
0/!
1.!
0~
0}
1|
1n
0^
0]
1\
b110100100 N
b100101 4!
b1000 X!
0K
0A
0?
05
04
13
1.
1-
0+
#7200
b100100 L
b110100101 !
b100110 "
b1000000000100101 #
b10000100101 $
b1 %
b100110 6
b10100101 7
b10000101 8
b110001 9
b1 :
b1001 C
b111 D
b110 E
b1011 F
b1 G
1j!
1h!
0d!
1c!
1`!
1\!
1V!
1T!
1L!
1D!
0<!
1;!
12!
10!
1~
0n
1m
1^
b100110 N
b10100101 4!
b111 X!
1K
1J
1I
0H
1;
14
0.
0-
#7400
b100101 L
b110100110 !
b100111 "
b1000000000100110 #
b10000100110 $
b10 %
b100111 6
b10100110 7
b10000110 8
b110010 9
b10 :
b1010 C
b1000 D
b111 E
b1100 F
b10 G
0j!
1i!
0h!
0g!
1f!
1d!
0`!
0_!
0^!
1]!
0\!
1[!
0V!
1U!
0T!
1S!
0L!
1K!
0D!
1C!
1<!
02!
11!
00!
1/!
0~
1}
1n
0^
1]
b1000000000100110 N
b10000110 4!
0B
1A
0=
1&
#7600
b100110 L
b110100111 !
b101000 "
b1000000000100111 #
b10000100111 $
b11 %
b101000 6
b10100111 7
b10000111 8
b110011 9
b11 :
b1011 C
b1001 D
b1000 E
b1101 F
b11 G
1j!
1h!
0d!
0c!
0b!
1a!
1`!
1\!
1V!
1T!
1L!
1D!
0<!
0;!
0:!
19!
12!
10!
1~
0n
0m
0l
1k
1^
b10000100111 N
b110011 4!
b1101 X!
0J
1H
1B
0@
1>
1=
0;
15
1+
0&
#7800
b100111 L
b110101000 !
b101001 "
b1000000000101000 #
b10000101000 $
b0 %
b101001 6
b10101000 7
b10001000 8
b110100 9
b0 :
b1100 C
b1010 D
b1001 E
b1110 F
b0 G
0j!
0i!
0h!
1g!
1d!
0`!
1_!
0\!
0[!
1Z!
0V!
0U!
0T!
0S!
1R!
0L!
0K!
0J!
1I!
0D!
0C!
0B!
1A!
1<!
02!
01!
00!
0/!
0.!
1-!
0~
0}
0|
1{
1n
0^
0]
0\
1[
b110101000 N
b101001 4!
b1100 X!
0K
0A
1?
0>
05
04
03
12
1.
1-
0+
#8000
b101000 L
b110101001 !
b101010 "
b1000000000101001 #
b10000101001 $
b1 %
b101010 6
b10101001 7
b10001001 8
b110101 9
b1 :
b1101 C
b1011 D
b1010 E
b1111 F
b1 G
1j!
1h!
0d!
1c!
1`!
1\!
1V!
1T!
1L!
1D!
0<!
1;!
12!
10!
1~
0n
1m
1^
b101010 N
b10101001 4!
b1011 X!
1K
1J
0I
1;
14
0.
0-
#8200
b101001 L
b110101010 !
b101011 "
b1000000000101010 #
b10000101010 $
b10 %
b101011 6
b10101010 7
b10001010 8
b110110 9
b10 :
b1110 C
b1100 D
b1011 E
b0 F
b10 G
0j!
1i!
0h!
0g!
0f!
0e!
1d!
0`!
0_!
1^!
0\!
1[!
0V!
1U!
0T!
1S!
0L!
1K!
0D!
1C!
1<!
02!
11!
00!
1/!
0~
1}
1n
0^
1]
b1000000000101010 N
b10001010 4!
0B
1A
0=
1&
#8400
b101010 L
b110101011 !
b101100 "
b1000000000101011 #
b10000101011 $
b11 %
b101100 6
b10101011 7
b10001011 8
b110111 9
b11 :
b1111 C
b1101 D
b1100 E
b1 F
b11 G
1j!
1h!
0d!
0c!
1b!
1`!
1\!
1V!
1T!
1L!
1D!
0<!
0;!
1:!
12!
10!
1~
0n
0m
1l
1^
b10000101011 N
b110111 4!
b1 X!
0J
0H
1B
1@
0?
1>
1=
0;
15
1+
0&
